embed_text_reducer/__init__.py
embed_text_reducer/reducer.py
embed_text_reducer-0.0.4.dist-info/LICENSE
embed_text_reducer-0.0.4.dist-info/METADATA
embed_text_reducer-0.0.4.dist-info/WHEEL
embed_text_reducer-0.0.4.dist-info/top_level.txt
embed_text_reducer-0.0.4.dist-info/RECORD
