Metadata-Version: 2.1
Name: embed-text-reducer
Version: 0.0.4
Summary: A simple text simplification tool using advanced NLP techniques.
Author-email: Danil Emelyanov <d.emelianov1991@gmail.com>
Project-URL: homepage, https://github.com/brokencop23/embed-text-reducer.git 
Project-URL: repository, https://github.com/brokencop23/embed-text-reducer.git 
Project-URL: documentation, https://github.com/brokencop23/embed-text-reducer.git#readme
Keywords: text,simplification,NLP
Classifier: Programming Language :: Python :: 3
Classifier: License :: OSI Approved :: MIT License
Classifier: Operating System :: OS Independent
Classifier: Intended Audience :: Developers
Classifier: Topic :: Text Processing :: Linguistic
License-File: LICENSE
Requires-Dist: numpy
Requires-Dist: tiktoken
Requires-Dist: sentence-transformers
Requires-Dist: scikit-learn
